{
    "subject": "pe2",
    "title": "스포츠 생활1/2 (김경래)",
    "subscript": "상상 이상으로 기능이 다채롭다",
    "cover_img_count": 2,
    "writing_staff": [
        {
            "name":"김경래", 
            "affiliation":"한국교원대학교 교수", 
            "history":["서울대학교 대학원 체육학 박사"],
            "word":"심신을 위한 에너지!"
        },
        {
            "name":"문제헌", 
            "affiliation":"한국교원대학교 교수", 
            "history":["서울대학교 대학원 체육학 박사"],
            "word":"생활 속 스포츠의 즐거움!"
        },
        {
            "name":"서건석", 
            "affiliation":"경기 삼성중학교 교사", 
            "history":["대진대학교 대학원 체육교육 석사"],
            "word":"체육의 정석 YBM 체육교과서"
        },
        {
            "name":"이병호", 
            "affiliation":"태장고등학교 교사", 
            "history":["용인대학교 대학원 교육행정 석사"],
            "word":"평생 건강을 위한 지침서"
        },
        {
            "name":"김철호", 
            "affiliation":"수원경기체육고등학교 교사", 
            "history":["경기대학교 대학원 체육교육 석사"],
            "word":"삶의 질을 향상시키는 교과서"
        },
        {
            "name":"정연규", 
            "affiliation":"부산체육중학교 교감", 
            "history":["부산외국어대학교 대학원 스포츠심리학 박사"],
            "word":"건강하고 활기찬 삶을 위한 바이블이다"
        },
        {
            "name":"김도형", 
            "affiliation":"광주 금호중앙여자고등학교 교사", 
            "history":["전남대학교 대학원 체육철학 박사"],
            "word":"스포츠의 생활화 교과서"
        },
        {
            "name":"고기범", 
            "affiliation":"강원 한국항공고등학교", 
            "history":["가톨릭관동대학교 졸업"],
            "word":"건강하고 행복한 삶의 완성"
        },
        {
            "name":"김광수", 
            "affiliation":"충북 동성고등학교 교사", 
            "history":["한국교원대학교 졸업"],
            "word":"평생 스포츠활동에 필요한 러닝메이트",
            "video":"https://kr.object.ncloudstorage.com/ybm-prd-std/interview/03-16.%20%EA%B3%A0%EB%93%B1%ED%95%99%EA%B5%90%20%EC%8A%A4%ED%8F%AC%EC%B8%A0%20%EC%83%9D%ED%99%9C1_2%20%EC%A0%80%EC%9E%90%20%EA%B9%80%EA%B4%91%EC%88%98%20%EC%84%A0%EC%83%9D%EB%8B%98%20%EC%9D%B8%ED%84%B0%EB%B7%B0%20%281%29.mp4"
        },
        {
            "name":"김남훈", 
            "affiliation":"동대전고등학교 교사", 
            "history":["한국교원대학교 졸업"],
            "word":"건강한 미래를 위한 투자서"
        },
        {
            "name":"김동민", 
            "affiliation":"광주 진남중학교", 
            "history":["한국교원대학교 졸업"],
            "word":"스포츠가 생활에 스며들다"
        },
        {
            "name":"김성민", 
            "affiliation":"한국교원대학교 학교체육연구소", 
            "history":["Beijing Sport Univ.(박사)"],
            "word":"건강을 위한 맞춤 운동 가이드"
        },
        {
            "name":"박성진", 
            "affiliation":"천안오성고등학교 교사", 
            "history":["가톨릭관동대학교 졸업"],
            "word":"스포츠 생활은 건강 생활"
        },
        {
            "name":"박현옥", 
            "affiliation":"울산 대현중학교", 
            "history":["가톨릭관동대학교 졸업"],
            "word":"스포츠는 생활"
        },
        {
            "name":"서승범", 
            "affiliation":"경북 경북소프트웨어고등학교", 
            "history":["경북대학교 대학원(석사)"],
            "word":"학생을 위한 노력의 결정체"
        },
        {
            "name":"안민지", 
            "affiliation":"한국교원대학교 학교체육연구소", 
            "history":["한국교원대학교 대학원 체육교육학과 박사"],
            "word":"리더십을 키우는 교과서"
        },
        {
            "name":"오연옥", 
            "affiliation":"전남 벌교여자중학교", 
            "history":["한국교원대학교 대학원(석사)"],
            "word":""
        },
        {
            "name":"이혜윤", 
            "affiliation":"세종 세종미래고등학교", 
            "history":["한국교원대학교 대학원(박사)"],
            "word":"생활에 스며든 스포츠 활동"
        },
        {
            "name":"정선목", 
            "affiliation":"서울 등촌고등학교", 
            "history":["경희대학교 졸업"],
            "word":"건강한 삶을 여는 열쇠!"
        }
    ],
    "character":[
        {"name":"스포츠 생활1"},
        {"name":"스포츠 생활2"}
    ],
    "booktab":[
        [
            "활동 중심의 교과서",
            "자기 주도적인 교과서",
            "창의성을 기르는 융합 선택 교과서"
        ],
        [
            "학습 안내를 제시한 지도서",
            "종목별 상식을 첨가한 지도서",
            "다양한 활동 자료를 제공한 지도서"
        ],
        [
            "한눈으로 보는 종목별 쉬운 선택",
            "종목별 활동별 동영상 제공",
            "다양한 교수학습 자료 제공"
        ]
    ]
}